graphinder/__init__.py
graphinder/__main__.py
graphinder/entities/__init__.py
graphinder/entities/errors.py
graphinder/entities/io.py
graphinder/entities/pool.py
graphinder/entities/tasks.py
graphinder/io/__init__.py
graphinder/io/printers.py
graphinder/io/providers.py
graphinder/io/readers.py
graphinder/io/writers.py
graphinder/main.py
graphinder/pool/__init__.py
graphinder/pool/detectors.py
graphinder/pool/domain.py
graphinder/pool/extractors.py
graphinder/pool/routine.py
graphinder/pool/tasks.py
graphinder/py.typed
graphinder/utils/__init__.py
graphinder/utils/assets.py
graphinder/utils/filters.py
graphinder/utils/finders.py
graphinder/utils/logger.py
graphinder/utils/webhook.py
graphinder-1.11.6.dist-info/entry_points.txt
graphinder-1.11.6.dist-info/LICENSE
graphinder-1.11.6.dist-info/WHEEL
graphinder-1.11.6.dist-info/METADATA
graphinder-1.11.6.dist-info/RECORD
