Metadata-Version: 2.1
Name: graphinder
Version: 1.11.6
Summary: Escape Graphinder
Home-page: https://escape.tech/
License: MIT
Author: Escape Technologies SAS
Author-email: ping@escape.tech
Maintainer: Karim Rustom
Maintainer-email: rustom@escape.tech
Requires-Python: >=3.10,<4.0
Classifier: License :: OSI Approved :: MIT License
Classifier: Programming Language :: Python :: 3
Classifier: Programming Language :: Python :: 3.10
Classifier: Programming Language :: Python :: 3.11
Requires-Dist: aiohttp[speedups] (>=3.8.1,<4.0.0)
Requires-Dist: beautifulsoup4 (>=4,<5)
Requires-Dist: requests (>=2.27.1,<3.0.0)
Project-URL: Bug Tracker, https://github.com/Escape-Technologies/graphinder/issues
Project-URL: Repository, https://github.com/Escape-Technologies/graphinder
